yaml2jsonnet/__init__.py
yaml2jsonnet/__main__.py
yaml2jsonnet/cli.py
yaml2jsonnet/jsonnet_renderer.py
yaml2jsonnet/yaml2jsonnet.py
yaml2jsonnet-1.0.1.dist-info/entry_points.txt
yaml2jsonnet-1.0.1.dist-info/LICENSE
yaml2jsonnet-1.0.1.dist-info/WHEEL
yaml2jsonnet-1.0.1.dist-info/METADATA
yaml2jsonnet-1.0.1.dist-info/RECORD
