Metadata-Version: 2.1
Name: yaml2jsonnet
Version: 1.0.1
Summary: Convert from YAML to Jsonnet format, retaining comments
Home-page: https://github.com/waisbrot/yaml2jsonnet
License: AGPL-3.0-or-later
Author: Nathaniel Waisbrot
Author-email: code@waisbrot.net
Requires-Python: >=3.8,<4.0
Classifier: Development Status :: 4 - Beta
Classifier: Environment :: Console
Classifier: Intended Audience :: Developers
Classifier: License :: OSI Approved :: GNU Affero General Public License v3 or later (AGPLv3+)
Classifier: Operating System :: POSIX
Classifier: Programming Language :: Python :: 3
Classifier: Programming Language :: Python :: 3.8
Classifier: Topic :: Software Development :: Compilers
Classifier: Topic :: Utilities
Requires-Dist: ruamel.yaml (>=0.16.10,<0.17.0)
Project-URL: Repository, https://github.com/waisbrot/yaml2jsonnet
